pyffstream/__init__.py
pyffstream/__main__.py
pyffstream/cli.py
pyffstream/encode.py
pyffstream/ffmpeg.py
pyffstream/py.typed
pyffstream-0.0.31.dist-info/entry_points.txt
pyffstream-0.0.31.dist-info/LICENSE
pyffstream-0.0.31.dist-info/WHEEL
pyffstream-0.0.31.dist-info/METADATA
pyffstream-0.0.31.dist-info/RECORD
