Metadata-Version: 2.1
Name: pyffstream
Version: 0.0.31
Summary: pyffstream.
Keywords: ffmpeg,streaming,srt,rtmp
Author-email: Gregory Beauregard <pyffstream@gably.net>
Requires-Python: >=3.9
Classifier: License :: OSI Approved :: MIT License
Classifier: Development Status :: 3 - Alpha
Classifier: Programming Language :: Python
Classifier: Programming Language :: Python :: 3.9
Classifier: Programming Language :: Python :: 3.10
Classifier: Programming Language :: Python :: 3.11
Classifier: Programming Language :: Python :: 3.12
Classifier: Typing :: Typed
Classifier: Environment :: Console
Requires-Dist: platformdirs >= 2.1.0
Requires-Dist: rich >= 10.15.0
Requires-Dist: requests
Requires-Dist: flit ; extra == "dev"
Requires-Dist: tox ; extra == "dev"
Requires-Dist: black ; extra == "dev"
Requires-Dist: isort ; extra == "dev"
Requires-Dist: mypy ; extra == "dev"
Requires-Dist: pyright ; extra == "dev"
Requires-Dist: sphinx ; extra == "docs"
Requires-Dist: sphinx_autodoc_typehints ; extra == "docs"
Requires-Dist: sphinxcontrib-autoprogram ; extra == "docs"
Project-URL: Source, https://github.com/GBeauregard/pyffstream
Provides-Extra: dev
Provides-Extra: docs
